resoto_plugin_aws_k8s/__init__.py
test/__init__.py
test/test_collector.py
resoto_plugin_aws_k8s-3.6.0.dist-info/METADATA
resoto_plugin_aws_k8s-3.6.0.dist-info/WHEEL
resoto_plugin_aws_k8s-3.6.0.dist-info/entry_points.txt
resoto_plugin_aws_k8s-3.6.0.dist-info/top_level.txt
resoto_plugin_aws_k8s-3.6.0.dist-info/RECORD
